README.md
daudin
setup.py
daudin.egg-info/PKG-INFO
daudin.egg-info/SOURCES.txt
daudin.egg-info/dependency_links.txt
daudin.egg-info/requires.txt
daudin.egg-info/top_level.txt
daudinlib/__init__.py
daudinlib/interaction.py
daudinlib/parse.py
daudinlib/pipeline.py
daudinlib/readline.py
test/test_interaction.py
test/test_parse.py
test/test_pipeline.py