Metadata-Version: 2.1
Name: daudin
Version: 0.0.19
Summary: A UNIX command-line shell based on Python
Home-page: https://github.com/terrycojones/daudin
Author: Terry Jones
Author-email: terry@jon.es
License: MIT
Download-URL: https://github.com/terrycojones/daudin
Keywords: python shell
Platform: UNKNOWN
Classifier: Development Status :: 3 - Alpha
Classifier: Environment :: Console
Classifier: Programming Language :: Python :: 3 :: Only
Classifier: Intended Audience :: Developers
Classifier: License :: OSI Approved :: MIT License
Classifier: Operating System :: MacOS :: MacOS X
Classifier: Operating System :: POSIX :: Linux
Classifier: Operating System :: Unix
Classifier: Topic :: System :: Shells
Provides-Extra: dev
